gh_store/__init__.py
gh_store/__main__.py
gh_store/default_config.yml
gh_store/cli/commands.py
gh_store/core/access.py
gh_store/core/constants.py
gh_store/core/exceptions.py
gh_store/core/store.py
gh_store/core/types.py
gh_store/core/version.py
gh_store/handlers/comment.py
gh_store/handlers/issue.py
gh_store/tools/canonicalize.py
gh_store-0.11.3.dist-info/METADATA
gh_store-0.11.3.dist-info/WHEEL
gh_store-0.11.3.dist-info/entry_points.txt
gh_store-0.11.3.dist-info/licenses/LICENSE
gh_store-0.11.3.dist-info/RECORD
