Metadata-Version: 2.4
Name: gh-store
Version: 0.11.3
Summary: A lightweight data store using GitHub Issues as a backend
Author-email: David Marx <david.marx84@gmail.com>
License: MIT
License-File: LICENSE
Requires-Python: <3.14,>=3.11.0
Requires-Dist: fire>=0.5.0
Requires-Dist: loguru>=0.7.2
Requires-Dist: omegaconf>=2.3.0
Requires-Dist: pygithub>=2.1.1
Requires-Dist: pyyaml>=6.0.1
Provides-Extra: dev
Requires-Dist: black>=23.12.0; extra == 'dev'
Requires-Dist: fastapi>=0.109.0; extra == 'dev'
Requires-Dist: httpx>=0.26.0; extra == 'dev'
Requires-Dist: isort>=5.13.0; extra == 'dev'
Requires-Dist: mypy>=1.8.0; extra == 'dev'
Requires-Dist: pytest-asyncio>=0.23.0; extra == 'dev'
Requires-Dist: pytest-cov>=4.1.0; extra == 'dev'
Requires-Dist: pytest>=7.4.0; extra == 'dev'
Requires-Dist: ruff>=0.1.9; extra == 'dev'
Requires-Dist: uvicorn>=0.27.0; extra == 'dev'
Provides-Extra: docs
Requires-Dist: mkdocs-material>=9.5.0; extra == 'docs'
Requires-Dist: mkdocs>=1.5.0; extra == 'docs'
Requires-Dist: mkdocstrings[python]>=0.24.0; extra == 'docs'
